pandem/__init__.py
pandem/pipeline.py
pandem/io/__init__.py
pandem/io/liggghts.py
pandem/io/mercury.py
pandem/io/nddem.py
pandem/io/nddem_vtk.py
pandem/io/utils.py
pandem/io/yade.py
pandem-0.3.1.dist-info/METADATA
pandem-0.3.1.dist-info/WHEEL
pandem-0.3.1.dist-info/entry_points.txt
pandem-0.3.1.dist-info/licenses/LICENSE.txt
pandem-0.3.1.dist-info/RECORD
