Metadata-Version: 2.4
Name: pandem
Version: 0.3.1
Summary: A python package for converting between DEM code output formats
Project-URL: Documentation, https://github.com/scigem/pandem/docs/index.html
Project-URL: Repository, https://github.com/scigem/pandem.git
Author-email: Benjy Marks <benjy.marks@sydney.edu.au>, François Guillard <francois.guillard@sydney.edu.au>
License-File: LICENSE.txt
Keywords: DEM,discrete element method,granular materials
Classifier: License :: OSI Approved :: GNU General Public License v3 or later (GPLv3+)
Requires-Python: >=3.8
Requires-Dist: black
Requires-Dist: flake8
Requires-Dist: nbsphinx
Requires-Dist: numpy
Requires-Dist: pandas
Requires-Dist: sphinx
Requires-Dist: vtk
